m2stitch/__init__.py
m2stitch/__main__.py
m2stitch/_constrained_refinement.py
m2stitch/_global_optimization.py
m2stitch/_stage_model.py
m2stitch/_translation_computation.py
m2stitch/_typing_utils.py
m2stitch/py.typed
m2stitch/stitching.py
m2stitch-0.7.0.dist-info/entry_points.txt
m2stitch-0.7.0.dist-info/LICENSE.rst
m2stitch-0.7.0.dist-info/WHEEL
m2stitch-0.7.0.dist-info/METADATA
m2stitch-0.7.0.dist-info/RECORD
