Metadata-Version: 2.1
Name: m2stitch
Version: 0.7.0
Summary: M2Stitch
Home-page: https://github.com/yfukai/m2stitch
License: MIT
Author: Yohsuke Fukai
Author-email: ysk@yfukai.net
Requires-Python: >=3.8,<3.11
Classifier: Development Status :: 3 - Alpha
Classifier: Intended Audience :: Developers
Classifier: Intended Audience :: Science/Research
Classifier: License :: OSI Approved :: MIT License
Classifier: Natural Language :: English
Classifier: Programming Language :: Python :: 3
Classifier: Programming Language :: Python :: 3.8
Classifier: Programming Language :: Python :: 3.9
Classifier: Programming Language :: Python :: 3.10
Classifier: Programming Language :: Python :: 3
Classifier: Programming Language :: Python :: 3.10
Classifier: Programming Language :: Python :: 3.8
Classifier: Programming Language :: Python :: 3.9
Requires-Dist: click (>=7,<9)
Requires-Dist: networkx (>=2.5.1,<3.0.0)
Requires-Dist: numpy (>=1.22,<2.0)
Requires-Dist: pandas (>=1.2.4,<2.0.0)
Requires-Dist: pandas-stubs (>=1.2.0,<1.3)
Requires-Dist: scikit-learn (>=1.0.2,<2.0.0)
Requires-Dist: scipy (>=1.6.3,<2.0.0)
Requires-Dist: tqdm (>=4.60.0,<5.0.0)
Project-URL: Changelog, https://github.com/yfukai/m2stitch/releases
Project-URL: Documentation, https://m2stitch.readthedocs.io
Project-URL: Repository, https://github.com/yfukai/m2stitch
